setup.py
src/erp5/__init__.py
src/erp5.recipe.cloudoooinstance.egg-info/PKG-INFO
src/erp5.recipe.cloudoooinstance.egg-info/SOURCES.txt
src/erp5.recipe.cloudoooinstance.egg-info/dependency_links.txt
src/erp5.recipe.cloudoooinstance.egg-info/entry_points.txt
src/erp5.recipe.cloudoooinstance.egg-info/namespace_packages.txt
src/erp5.recipe.cloudoooinstance.egg-info/not-zip-safe
src/erp5.recipe.cloudoooinstance.egg-info/requires.txt
src/erp5.recipe.cloudoooinstance.egg-info/top_level.txt
src/erp5/recipe/__init__.py
src/erp5/recipe/cloudoooinstance/CHANGES.txt
src/erp5/recipe/cloudoooinstance/__init__.py
src/erp5/recipe/cloudoooinstance/cloudooo.conf.in
src/erp5/recipe/cloudoooinstance/cloudoooctl.in