Metadata-Version: 1.0
Name: erp5.recipe.cloudoooinstance
Version: 0.0.8
Summary: ZC Buildout recipe for installing a cloudooo instance
Home-page: UNKNOWN
Author: Gabriel M. Monnerat
Author-email: gabriel@tiolive.com
License: ZPL 2.1
Keywords: cloud buildout
Platform: UNKNOWN
Classifier: License :: OSI Approved :: Zope Public License
Classifier: Framework :: Buildout
